CHANGELOG.md
langtree/__init__.py
langtree/core/__init__.py
langtree/core/buffer.py
langtree/core/operator.py
langtree/core/prompt.py
langtree/core/utils.py
langtree/core/vectordb.py
langtree/models/__init__.py
langtree/models/openai/__init__.py
langtree/models/openai/openai_adapter.py
langtree/operators/__init__.py
langtree/operators/base_operators.py
langtree/prompting/__init__.py
langtree/prompting/message_types.py
langtree/utils/__init__.py
langtree/utils/data.py
langtree/vectordb/__init__.py
langtree-0.1.1.dist-info/LICENSE
langtree-0.1.1.dist-info/METADATA
langtree-0.1.1.dist-info/WHEEL
langtree-0.1.1.dist-info/RECORD
