Metadata-Version: 2.1
Name: langtree
Version: 0.1.1
Summary: A minimalist python library for LLMs. Our mission is to reduce the mental overhead of developers interacting with language models. This perhead required to interact with language models without making you leave your framework of choice.
License: MIT
Author: EntropyAI
Requires-Python: >=3.9,<4.0
Classifier: License :: OSI Approved :: MIT License
Classifier: Programming Language :: Python :: 3
Classifier: Programming Language :: Python :: 3.9
Classifier: Programming Language :: Python :: 3.10
Classifier: Programming Language :: Python :: 3.11
Requires-Dist: backoff (>=2.2.1,<3.0.0)
Requires-Dist: openai (>=0.27.8,<0.28.0)
